[
  {
    "product_type": "",
    "name": "hhjjgj"
  },
  {
    "product_type": "",
    "name": "hghg"
  },
  {
    "product_type": "",
    "name": "sdds"
  },
  {
    "product_type": "",
    "name": "fdf"
  },
  {
    "product_type": "",
    "name": "drfdf"
  },
  {
    "product_type": "",
    "name": "abcd"
  },
  {
    "product_type": "",
    "name": "efgh"
  },
  {
    "product_type": "",
    "name": "HG HG"
  },
  {
    "product_type": "",
    "name": "dfdf"
  },
  {
    "product_type": "",
    "name": "dfdfv"
  },
  {
    "product_type": "",
    "name": "dff"
  },
  {
    "product_type": "",
    "name": "sdvv"
  },
  {
    "product_type": "",
    "name": "vzd"
  },
  {
    "product_type": "",
    "name": "hggh"
  },
  {
    "product_type": "",
    "name": "jjj"
  },
  {
    "product_type": "",
    "name": "ghg"
  },
  {
    "product_type": "",
    "name": "dfdfcvbv"
  },
  {
    "product_type": "",
    "name": "gffvvv"
  },
  {
    "product_type": "",
    "name": "vbnnn"
  },
  {
    "product_type": "",
    "name": "xcvf"
  },
  {
    "product_type": "",
    "name": "mnbfgf"
  },
  {
    "product_type": "",
    "name": "cvvff"
  },
  {
    "product_type": "",
    "name": "bvbvbyfg"
  },
  {
    "product_type": "",
    "name": "yuyrtg"
  },
  {
    "product_type": "",
    "name": "bbvbvb"
  },
  {
    "product_type": "",
    "name": "vcbvbvb"
  },
  {
    "product_type": "",
    "name": "moiop"
  },
  {
    "product_type": "",
    "name": "pljgf"
  },
  {
    "product_type": "",
    "name": "dfvvbb"
  },
  {
    "product_type": "",
    "name": "sddsd"
  },
  {
    "product_type": "",
    "name": "dfsdfsf"
  }
]